CHANGELOG.md
airlift_py/__init__.py
airlift_py/__main__.py
airlift_py/airlift_data_guesser.py
airlift_py/airtable_client.py
airlift_py/airtable_error_handling.py
airlift_py/airtable_upload.py
airlift_py/cli.py
airlift_py/cli_args.py
airlift_py/csv_data.py
airlift_py/dropbox_client.py
airlift_py/json_data.py
airlift_py/utils_exceptions.py
airlift_py/version.py
airlift_py-1.0.0.dist-info/LICENSE
airlift_py-1.0.0.dist-info/METADATA
airlift_py-1.0.0.dist-info/WHEEL
airlift_py-1.0.0.dist-info/entry_points.txt
airlift_py-1.0.0.dist-info/RECORD
