Metadata-Version: 2.1
Name: airlift-py
Version: 1.0.0
Summary: Upload & Merge Data with Attachments to Airtable
Home-page: https://github.com/TheAcharya/Airlift
License: MIT
Keywords: csv,json,airtable,dropbox,import,merge
Author: Arjun
Author-email: arjunprakash027@gmail.com
Requires-Python: >=3.8,<4.0
Classifier: Development Status :: 4 - Beta
Classifier: Environment :: Console
Classifier: Intended Audience :: End Users/Desktop
Classifier: License :: OSI Approved :: MIT License
Classifier: Natural Language :: English
Classifier: Operating System :: MacOS
Classifier: Operating System :: Microsoft
Classifier: Operating System :: Unix
Classifier: Programming Language :: Python :: 3
Classifier: Programming Language :: Python :: 3.8
Classifier: Programming Language :: Python :: 3.9
Classifier: Programming Language :: Python :: 3.10
Classifier: Programming Language :: Python :: 3.11
Classifier: Topic :: Database
Classifier: Topic :: Internet
Classifier: Topic :: Terminals
Classifier: Topic :: Utilities
Requires-Dist: dropbox (>=11.36.2,<12.0.0)
Requires-Dist: pyairtable (>=2.1.0.post1,<3.0.0)
Requires-Dist: requests (>=2.31.0,<3.0.0)
Requires-Dist: tqdm (>=4.66.1,<5.0.0)
Project-URL: Documentation, https://github.com/TheAcharya/Airlift/blob/main/README.md
Project-URL: Repository, https://github.com/TheAcharya/Airlift
